package_name/__init__.py
package_name/file1_name.py
package_name/file2_name.py
package_name_para_teste_DIO-0.0.1.dist-info/METADATA
package_name_para_teste_DIO-0.0.1.dist-info/WHEEL
package_name_para_teste_DIO-0.0.1.dist-info/top_level.txt
package_name_para_teste_DIO-0.0.1.dist-info/RECORD
