Metadata-Version: 2.1
Name: package_name_para_teste_DIO
Version: 0.0.1
Summary: Teste
Home-page: https://github.com/BartBoy0/simple-package-template
Author: Alex
Requires-Python: >=3.8
